odoo8_addon_hr_expense_account_period-8.0.0.1.0.99.dev7-py2.7-nspkg.pth
odoo8_addon_hr_expense_account_period-8.0.0.1.0.99.dev7.dist-info/DESCRIPTION.rst
odoo8_addon_hr_expense_account_period-8.0.0.1.0.99.dev7.dist-info/METADATA
odoo8_addon_hr_expense_account_period-8.0.0.1.0.99.dev7.dist-info/RECORD
odoo8_addon_hr_expense_account_period-8.0.0.1.0.99.dev7.dist-info/WHEEL
odoo8_addon_hr_expense_account_period-8.0.0.1.0.99.dev7.dist-info/metadata.json
odoo8_addon_hr_expense_account_period-8.0.0.1.0.99.dev7.dist-info/namespace_packages.txt
odoo8_addon_hr_expense_account_period-8.0.0.1.0.99.dev7.dist-info/top_level.txt
odoo_addons/hr_expense_account_period/README.rst
odoo_addons/hr_expense_account_period/__init__.py
odoo_addons/hr_expense_account_period/__openerp__.py
odoo_addons/hr_expense_account_period/i18n/de.po
odoo_addons/hr_expense_account_period/i18n/es.po
odoo_addons/hr_expense_account_period/i18n/fi.po
odoo_addons/hr_expense_account_period/i18n/fr.po
odoo_addons/hr_expense_account_period/i18n/hr_expense_account_period.pot
odoo_addons/hr_expense_account_period/i18n/pt_BR.po
odoo_addons/hr_expense_account_period/i18n/sl.po
odoo_addons/hr_expense_account_period/models/__init__.py
odoo_addons/hr_expense_account_period/models/hr_expense.py
odoo_addons/hr_expense_account_period/static/description/icon.png
odoo_addons/hr_expense_account_period/tests/__init__.py
odoo_addons/hr_expense_account_period/tests/test_hr_expense_journal.py
odoo_addons/hr_expense_account_period/view/hr_expense_view.xml
